demiurg/__init__.py
demiurg/agent.py
demiurg/exceptions.py
demiurg/messaging.py
demiurg/models.py
demiurg/providers/__init__.py
demiurg/providers/base.py
demiurg/providers/openai.py
demiurg/scheduled_agent.py
demiurg/tool_registry.py
demiurg/tools/__init__.py
demiurg/tools/composio.py
demiurg/tools/openai_tools.py
demiurg/utils/__init__.py
demiurg/utils/audio.py
demiurg/utils/files.py
demiurg/utils/logging.py
demiurg/utils/scheduling.py
demiurg/utils/tools.py
demiurg-0.1.52.dist-info/LICENSE
demiurg-0.1.52.dist-info/METADATA
demiurg-0.1.52.dist-info/WHEEL
demiurg-0.1.52.dist-info/RECORD
