Metadata-Version: 2.3
Name: demiurg
Version: 0.1.52
Summary: AI Agent Framework for building intelligent agents with multiple LLM providers
License: Proprietary
Keywords: ai,agents,llm,openai,chatbot
Author: Demiurg AI
Author-email: support@demiurg.ai
Requires-Python: >=3.9,<4.0
Classifier: Development Status :: 3 - Alpha
Classifier: Intended Audience :: Developers
Classifier: License :: Other/Proprietary License
Classifier: Programming Language :: Python :: 3
Classifier: Programming Language :: Python :: 3.9
Classifier: Programming Language :: Python :: 3.10
Classifier: Programming Language :: Python :: 3.11
Classifier: Programming Language :: Python :: 3.12
Classifier: Programming Language :: Python :: 3.13
Requires-Dist: apscheduler (>=3.10.0,<4.0.0)
Requires-Dist: composio (>=0.8.0,<0.9.0)
Requires-Dist: composio-openai (>=0.8.0,<0.9.0)
Requires-Dist: croniter (>=2.0.0,<3.0.0)
Requires-Dist: httpx (>=0.25.0,<0.26.0)
Requires-Dist: openai (>=1.0.0,<2.0.0)
Requires-Dist: pydantic (>=2.0.0,<3.0.0)
Requires-Dist: python-dateutil (>=2.8.0,<3.0.0)
Project-URL: Documentation, https://docs.demiurg.ai
Project-URL: Homepage, https://demiurg.ai
